Workbook

Sheet components
A1: uuid | B1: category | C1: number | D1: name | E1: description | F1: revision | G1: lifecycle_state | H1: owner | I1: material | J1: cad_file_name | K1: cad_file_link | L1: supplier_uuid | M1: supplier_name | N1: unit_price | O1: currency
A2: 393e864e-a7e8-4ed3-96cc-e3af45ee3e85 | B2: STD | C2: 000001 | D2: Bolt ISO 4762 M3x5 | E2: A hexagon socket head cap bolt for fastening metal parts | F2: 1 | G2: In Work | H2: Max Mustermann | I2: Stainless Steel | J2: ISO4762_M3x5.FCStd | K2: =HYPERLINK("components-cad/" & J2) -> components-cad/ISO4762_M3x5.FCStd | L2: 89e1cda9-c5eb-4705-86af-b27eace05a4d | M2: =IFERROR(VLOOKUP(L2, suppliers!$A$1:$Z$1000, 2, 0), "Enter a valid uuid in the supplier_uuid column") -> Adolf Würth GmbH & Co. KG | N2: 0.1 | O2: EUR
A3: 2f49c9f4-1a10-4b66-b86c-e58b0930d040 | B3: STD | C3: 000002 | D3: Bolt ISO 4762 M3x6 | E3: A hexagon socket head cap bolt for fastening metal parts | F3: 1 | G3: In Work | H3: Max Mustermann | I3: Stainless Steel | J3: ISO4762_M3x6.FCStd | K3: =HYPERLINK("components-cad/" & J3) -> components-cad/ISO4762_M3x6.FCStd | L3: 89e1cda9-c5eb-4705-86af-b27eace05a4d | M3: =IFERROR(VLOOKUP(L3, suppliers!$A$1:$Z$1000, 2, 0), "Enter a valid uuid in the supplier_uuid column") -> Adolf Würth GmbH & Co. KG | N3: 0.1 | O3: EUR
A4: 5dca19b4-36df-45ab-9675-d1e4175f3808 | B4: STD | C4: 000003 | D4: Bolt ISO 4762 M3x8 | E4: A hexagon socket head cap bolt for fastening metal parts | F4: 1 | G4: In Work | H4: Max Mustermann | I4: Stainless Steel | J4: ISO4762_M3x8.FCStd | K4: =HYPERLINK("components-cad/" & J4) -> components-cad/ISO4762_M3x8.FCStd | L4: 89e1cda9-c5eb-4705-86af-b27eace05a4d | M4: =IFERROR(VLOOKUP(L4, suppliers!$A$1:$Z$1000, 2, 0), "Enter a valid uuid in the supplier_uuid column") -> Adolf Würth GmbH & Co. KG | N4: 0.1 | O4: EUR
A5: a8b63aee-3999-42c3-8c9f-0e92af577356 | B5: STD | C5: 000004 | D5: Bolt ISO 4762 M3x10 | E5: A hexagon socket head cap bolt for fastening metal parts | F5: 1 | G5: In Work | H5: Max Mustermann | I5: Stainless Steel | J5: ISO4762_M3x10.FCStd | K5: =HYPERLINK("components-cad/" & J5) -> components-cad/ISO4762_M3x10.FCStd | L5: 89e1cda9-c5eb-4705-86af-b27eace05a4d | M5: =IFERROR(VLOOKUP(L5, suppliers!$A$1:$Z$1000, 2, 0), "Enter a valid uuid in the supplier_uuid column") -> Adolf Würth GmbH & Co. KG | N5: 0.1 | O5: EUR
A6: 435e41de-ebf3-4ce8-9a77-9ac3a9cb2bf3 | B6: STD | C6: 000005 | D6: Bolt ISO 4762 M3x12 | E6: A hexagon socket head cap bolt for fastening metal parts | F6: 1 | G6: In Work | H6: Max Mustermann | I6: Stainless Steel | J6: ISO4762_M3x12.FCStd | K6: =HYPERLINK("components-cad/" & J6) -> components-cad/ISO4762_M3x12.FCStd | L6: 89e1cda9-c5eb-4705-86af-b27eace05a4d | M6: =IFERROR(VLOOKUP(L6, suppliers!$A$1:$Z$1000, 2, 0), "Enter a valid uuid in the supplier_uuid column") -> Adolf Würth GmbH & Co. KG | N6: 0.1 | O6: EUR
A7: 188e331a-acd1-45d2-9701-83cd6e858f86 | B7: STD | C7: 000006 | D7: Bolt ISO 4762 M3x14 | E7: A hexagon socket head cap bolt for fastening metal parts | F7: 1 | G7: In Work | H7: Max Mustermann | I7: Stainless Steel | J7: ISO4762_M3x14.FCStd | K7: =HYPERLINK("components-cad/" & J7) -> components-cad/ISO4762_M3x14.FCStd | L7: 89e1cda9-c5eb-4705-86af-b27eace05a4d | M7: =IFERROR(VLOOKUP(L7, suppliers!$A$1:$Z$1000, 2, 0), "Enter a valid uuid in the supplier_uuid column") -> Adolf Würth GmbH & Co. KG | N7: 0.1 | O7: EUR
A8: 848ed85c-ffda-4458-a6cf-5ff1eb394e35 | B8: STD | C8: 000007 | D8: Bolt ISO 4762 M3x16 | E8: A hexagon socket head cap bolt for fastening metal parts | F8: 1 | G8: In Work | H8: Max Mustermann | I8: Stainless Steel | J8: ISO4762_M3x16.FCStd | K8: =HYPERLINK("components-cad/" & J8) -> components-cad/ISO4762_M3x16.FCStd | L8: 89e1cda9-c5eb-4705-86af-b27eace05a4d | M8: =IFERROR(VLOOKUP(L8, suppliers!$A$1:$Z$1000, 2, 0), "Enter a valid uuid in the supplier_uuid column") -> Adolf Würth GmbH & Co. KG | N8: 0.1 | O8: EUR
A9: 6afc24c5-5060-45a2-98a6-aac580ea6dd8 | B9: STD | C9: 000008 | D9: Bolt ISO 4762 M3x20 | E9: A hexagon socket head cap bolt for fastening metal parts | F9: 1 | G9: In Work | H9: Max Mustermann | I9: Stainless Steel | J9: ISO4762_M3x20.FCStd | K9: =HYPERLINK("components-cad/" & J9) -> components-cad/ISO4762_M3x20.FCStd | L9: 89e1cda9-c5eb-4705-86af-b27eace05a4d | M9: =IFERROR(VLOOKUP(L9, suppliers!$A$1:$Z$1000, 2, 0), "Enter a valid uuid in the supplier_uuid column") -> Adolf Würth GmbH & Co. KG | N9: 0.1 | O9: EUR
A10: 5fc9beb5-1216-4e89-abc1-4fbd9fc3c844 | B10: STD | C10: 000009 | D10: Bolt ISO 4762 M3x25 | E10: A hexagon socket head cap bolt for fastening metal parts | F10: 1 | G10: In Work | H10: Max Mustermann | I10: Stainless Steel | J10: ISO4762_M3x25.FCStd | K10: =HYPERLINK("components-cad/" & J10) -> components-cad/ISO4762_M3x25.FCStd | L10: 89e1cda9-c5eb-4705-86af-b27eace05a4d | M10: =IFERROR(VLOOKUP(L10, suppliers!$A$1:$Z$1000, 2, 0), "Enter a valid uuid in the supplier_uuid column") -> Adolf Würth GmbH & Co. KG | N10: 0.1 | O10: EUR
A11: 6da2491d-e10a-41f8-8803-eb7486429715 | B11: STD | C11: 000010 | D11: Bolt ISO 4762 M3x30 | E11: A hexagon socket head cap bolt for fastening metal parts | F11: 1 | G11: In Work | H11: Max Mustermann | I11: Stainless Steel | J11: ISO4762_M3x30.FCStd | K11: =HYPERLINK("components-cad/" & J11) -> components-cad/ISO4762_M3x30.FCStd | L11: 89e1cda9-c5eb-4705-86af-b27eace05a4d | M11: =IFERROR(VLOOKUP(L11, suppliers!$A$1:$Z$1000, 2, 0), "Enter a valid uuid in the supplier_uuid column") -> Adolf Würth GmbH & Co. KG | N11: 0.1 | O11: EUR
A12: 619dab0d-cb6a-42f0-ad56-265287a4e9d3 | B12: STD | C12: 000011 | D12: Bolt ISO 4762 M4x6 | E12: A hexagon socket head cap bolt for fastening metal parts | F12: 1 | G12: In Work | H12: Max Mustermann | I12: Stainless Steel | J12: ISO4762_M4x6.FCStd | K12: =HYPERLINK("components-cad/" & J12) -> components-cad/ISO4762_M4x6.FCStd | L12: 89e1cda9-c5eb-4705-86af-b27eace05a4d | M12: =IFERROR(VLOOKUP(L12, suppliers!$A$1:$Z$1000, 2, 0), "Enter a valid uuid in the supplier_uuid column") -> Adolf Würth GmbH & Co. KG | N12: 0.1 | O12: EUR
A13: b49a451f-edd6-4f82-98b7-4b8eb61ecb6e | B13: STD | C13: 000012 | D13: Bolt ISO 4762 M4x8 | E13: A hexagon socket head cap bolt for fastening metal parts | F13: 1 | G13: In Work | H13: Max Mustermann | I13: Stainless Steel | J13: ISO4762_M4x8.FCStd | K13: =HYPERLINK("components-cad/" & J13) -> components-cad/ISO4762_M4x8.FCStd | L13: 89e1cda9-c5eb-4705-86af-b27eace05a4d | M13: =IFERROR(VLOOKUP(L13, suppliers!$A$1:$Z$1000, 2, 0), "Enter a valid uuid in the supplier_uuid column") -> Adolf Würth GmbH & Co. KG | N13: 0.1 | O13: EUR
... A121: 537a5c45-85aa-4fa4-857c-5d48b9be8a47 | B121: MECH | C121: 000120 | D121: Aluminum profile mk 2060.05 1800 mm | E121: The Series 60 aluminum profiles are heavy-duty 60x60 modular profiles designed for maximum load capacity. | F121: 1 | G121: In Work | H121: Max Mustermann | I121: Stainless Steel | J121: mk_2060.05_1800.FCStd | K121: =HYPERLINK("components-cad/" & J121) -> components-cad/mk_2060.05_1800.FCStd | L121: 89e1cda9-c5eb-4705-86af-b27eace05a4d | M121: =IFERROR(VLOOKUP(L121, suppliers!$A$1:$Z$1000, 2, 0), "Enter a valid uuid in the supplier_uuid column") -> Adolf Würth GmbH & Co. KG | N121: 0.1 | O121: EUR
A122: f15a570b-3fa3-44dd-a034-4f8c5efacdb5 | F122: 1 | G122: In Work | H122: Max Mustermann | I122: Stainless Steel | M122: =IFERROR(VLOOKUP(L122, suppliers!$A$1:$Z$1000, 2, 0), "Enter a valid uuid in the supplier_uuid column") -> Enter a valid uuid in the supplier_uuid column | N122: 0.1 | O122: EUR
A123: 8311133e-21da-4966-8260-60a646333619 | F123: 1 | G123: In Work | H123: Max Mustermann | I123: Stainless Steel | M123: =IFERROR(VLOOKUP(L123, suppliers!$A$1:$Z$1000, 2, 0), "Enter a valid uuid in the supplier_uuid column") -> Enter a valid uuid in the supplier_uuid column | N123: 0.1 | O123: EUR
A124: d38c4046-8f04-416c-8064-d3f7fbc1a0bf | F124: 1 | G124: In Work | H124: Max Mustermann | I124: Stainless Steel | M124: =IFERROR(VLOOKUP(L124, suppliers!$A$1:$Z$1000, 2, 0), "Enter a valid uuid in the supplier_uuid column") -> Enter a valid uuid in the supplier_uuid column | N124: 0.1 | O124: EUR
A125: 3d46537b-4cee-4c0f-9e33-77bfa4894de6 | F125: 1 | G125: In Work | H125: Max Mustermann | I125: Stainless Steel | M125: =IFERROR(VLOOKUP(L125, suppliers!$A$1:$Z$1000, 2, 0), "Enter a valid uuid in the supplier_uuid column") -> Enter a valid uuid in the supplier_uuid column | N125: 0.1 | O125: EUR
A126: 103d96ce-795a-4df5-afe1-345283c95a1d | F126: 1 | G126: In Work | H126: Max Mustermann | I126: Stainless Steel | M126: =IFERROR(VLOOKUP(L126, suppliers!$A$1:$Z$1000, 2, 0), "Enter a valid uuid in the supplier_uuid column") -> Enter a valid uuid in the supplier_uuid column | N126: 0.1 | O126: EUR
A127: f36ec171-04a1-4b45-8a94-56ba1503885b | F127: 1 | G127: In Work | H127: Max Mustermann | I127: Stainless Steel | M127: =IFERROR(VLOOKUP(L127, suppliers!$A$1:$Z$1000, 2, 0), "Enter a valid uuid in the supplier_uuid column") -> Enter a valid uuid in the supplier_uuid column | N127: 0.1 | O127: EUR
A128: 5c81ed71-a0a2-43e0-8fd3-25dfb3c8a56a | F128: 1 | G128: In Work | H128: Max Mustermann | I128: Stainless Steel | M128: =IFERROR(VLOOKUP(L128, suppliers!$A$1:$Z$1000, 2, 0), "Enter a valid uuid in the supplier_uuid column") -> Enter a valid uuid in the supplier_uuid column | N128: 0.1 | O128: EUR
A129: 63bd1ea0-da80-4d1d-aad6-cf1831b8eb1c | F129: 1 | G129: In Work | H129: Max Mustermann | I129: Stainless Steel | M129: =IFERROR(VLOOKUP(L129, suppliers!$A$1:$Z$1000, 2, 0), "Enter a valid uuid in the supplier_uuid column") -> Enter a valid uuid in the supplier_uuid column | N129: 0.1 | O129: EUR
A130: b78c4bb7-bbd0-4902-8c4c-4d948b4f439c | F130: 1 | G130: In Work | H130: Max Mustermann | I130: Stainless Steel | M130: =IFERROR(VLOOKUP(L130, suppliers!$A$1:$Z$1000, 2, 0), "Enter a valid uuid in the supplier_uuid column") -> Enter a valid uuid in the supplier_uuid column | N130: 0.1 | O130: EUR
A131: e9246667-4493-4e30-874b-460b0676ab46 | F131: 1 | G131: In Work | H131: Max Mustermann | I131: Stainless Steel | M131: =IFERROR(VLOOKUP(L131, suppliers!$A$1:$Z$1000, 2, 0), "Enter a valid uuid in the supplier_uuid column") -> Enter a valid uuid in the supplier_uuid column | N131: 0.1 | O131: EUR
A132: ac3b813f-aed5-438e-9b56-d5c53a298cb4 | F132: 1 | G132: In Work | H132: Max Mustermann | I132: Stainless Steel | M132: =IFERROR(VLOOKUP(L132, suppliers!$A$1:$Z$1000, 2, 0), "Enter a valid uuid in the supplier_uuid column") -> Enter a valid uuid in the supplier_uuid column | N132: 0.1 | O132: EUR
A133: a95517bf-aa70-4185-af9a-723032c78b9d | F133: 1 | G133: In Work | H133: Max Mustermann | I133: Stainless Steel | M133: =IFERROR(VLOOKUP(L133, suppliers!$A$1:$Z$1000, 2, 0), "Enter a valid uuid in the supplier_uuid column") -> Enter a valid uuid in the supplier_uuid column | N133: 0.1 | O133: EUR
... A461: 9b310d6c-a6b2-4c1e-8056-d0b21460a17b | F461: 1 | G461: In Work | H461: Max Mustermann | I461: Stainless Steel | M461: =IFERROR(VLOOKUP(L461, suppliers!$A$1:$Z$1000, 2, 0), "Enter a valid uuid in the supplier_uuid column") -> Enter a valid uuid in the supplier_uuid column | N461: 0.1 | O461: EUR

Sheet suppliers
A1: uuid | B1: name | C1: description | D1: street | E1: street_number | F1: postal_code | G1: city | H1: country
A2: 89e1cda9-c5eb-4705-86af-b27eace05a4d | B2: Adolf Würth GmbH & Co. KG | C2: The Würth Group is a leader in the development, manufacture, and distribution of assembly and fastening materials. The globally active family-owned company, headquartered in Künzelsau, Germany, comprises over 400 subsidiaries with over 2,800 branches in 80 countries. | D2: Reinhold-Würth-Straße | E2: 12 | F2: 74653 | G2: Künzelsau-Gaisbach | H2: Deutschland
A3: bf0746cd-2e6c-4468-9538-0854b1bd9d06 | B3: Robert Bosch GmbH | C3: The Bosch Group is a leading international supplier of technology and services with approximately 418,000 associates worldwide (as of December 31, 2024). | D3: Robert-Bosch-Platz | E3: 1 | F3: 70839 | G3: Gerlingen-Schillerhöhe | H3: Deutschland
A4: f6e7fa76-e9f0-40d4-88d0-faba2831f6d8 | B4: ALSADO Inh. Aleksander Sadowski | C4: ALSADO is a small company in Sankt Augustin in Germany, which specializes in CAD and PDM/PLM software development. Recetnly ALSADO is also entering the hardward manufacturing market with its innovative fastening solution for safery applications. | D4: Liebfrauenstraße | E4: 31 | F4: 53757 | G4: Sankt Augustin | H4: Deutschland
A5: ec6514ad-e6eb-4181-9757-e34571fbdb1d | B5: Xometry Europe GmbH | C5: Xometry’s (NASDAQ: XMTR) AI-powered marketplace and suite of cloud-based services are rapidly digitising the manufacturing industry. | D5: Ada-Lovelace-Straße | E5: 9 | F5: 85521 | G5: Ottobrunn | H5: Deutschland
A6: 25a21235-6c6b-4878-8716-5ea914db9d75 | B6: Maschinenbau Kitz GmbH | C6: Maschinenbau Kitz GmbH, founded in 1966 in Troisdorf near Bonn, Germany, is the parent company of the mk Technology Group, a leading provider of modular systems for factory automation, specializing in aluminum profile systems, conveyor technology, and custom engineering solutions for various industries. | D6: Ampèrestraße | E6: 18 | F6: 53844 | G6: Troisdorf | H6: Deutschland
A7: 2f6a25b9-b96c-4135-b468-737c9e7ee1a6
A8: 27b96fd9-1b69-4009-91ea-67bdb650a0a1
A9: f869e1ed-2d68-4f61-bf59-c7d18844d6d5
A10: d649381b-b6a9-4b83-9641-90ed071e0ff7
A11: c92efca7-d5d8-47c4-abc9-1b61a0edcd98
A12: 2b4e8ca6-ce77-4ceb-98f5-5c0fa12a7841
A13: aa1044c2-6806-48db-8d2e-6b81852d53cc
A14: d4b3e26d-474f-482b-b856-1942fe0feef1
A15: 34fa6f8b-1235-44a0-b52b-8988d9ad2e65
A16: 0776124a-ac7a-422e-955d-f8f6024a7180
A17: 1dfabe57-5007-4706-bec2-5504f0e2102a
A18: 3cfa69c7-9fac-4d1d-b76b-88f95c5ba8e0
... A41: c673b3b3-29e4-47df-9e9d-a9911c6e1ae8

Sheet numbering_system
A1: number | B1: description
A2: MECH | B2: Mechanical Components; Includes all physical, non-electrical parts used in assemblies (e.g. brackets, frames, fasteners, gears, shafts, bearings, housings, springs).
A3: ELEC | B3: Electrical/Electronic Components; Includes all parts that carry or control electrical signals (e.g. PCBs, wiring harnesses, connectors, sensors, switches, motors, actuators).
A4: SW | B4: Software/Firmware; Includes control software, embedded firmware, and other digital configurations used in products.
A5: STD | B5: Standard/Commercial Off-The-Shelf Components; Includes commonly available items sourced from suppliers (e.g. fasteners, bearings, resistors, capacitors, relays).
A6: MAT | B6: Raw Materials; Includes unprocessed materials used in production (e.g. sheet metal, plastics, aluminum profiles, rubber, chemicals).
A7: TFC | B7: Tools, Fixtures, and Consumables; Includes items used in manufacturing or maintenance that do not become part of the finished product (e.g. jigs, fixtures, hand tools, lubricants, cutting fluids).
A8: PKG | B8: Packaging and Shipping Materials; Includes materials used to store, protect, or ship products (e.g. boxes, pallets, bubble wrap, labels).

Sheet values
A1: VAT | B1: assembly cost (hourly rate) | C1: unit_assembly_time
A2: 0.19 | B2: 14.2 | C2: 2

Sheet invoice
A8: Aleksander Sadowski | Liebfrauenstraße 31 | 53757 Sankt Augustin
A10: Mustermann GmbH
A11: Musterstraße 17
A12: 123456 Musterstadt
A13: Musterland
F14: Angebots-Nr.: | G14: 9
F15: Kundennummer: | G15: 40
F16: Angebotsdatum: | G16: 45951
A18: Angebot
A20: Wir bedanken uns für das Interesse an unseren Dienstleistungen und möchten Ihnen folgendes Angebot unterbreiten:
A22: Pos. | B22: Bezeichnung | G22: Preis
A23: 1 | G23: 100
A24: Total | G24: =SUM(G23) -> 100
A28: Der volle Betrag ist spätestens 30 Tage nach Lieferung auf das unten angegebene Konto zu überweisen. Mit freundlichen Grüßen Aleksander Sadowski

Sheet boms
A1: uuid | B1: bom_id | C1: name | D1: number of components (total) | E1: cost of parts (total) | F1: assembly time (h) | G1: assembly cost (hourly rate) | H1: assembly cost (total) | I1: manufacturing cost (total) | J1: profit margin | K1: profit | L1: selling price (net) | M1: VAT rate | N1: VAT amount | O1: selling price (gross)
A2: 00622a2a-0f53-454a-bd9b-1c2583f1ec92 | B2: bom_00001 | C2: Parts loader for EMCO F1 CNC | D2: =IF(C2<>"", SUM(INDEX(INDIRECT("'" & B2 & "'.$A$1:$Z$1000"), 0, MATCH("count", INDIRECT("'" & B2 & "'.$A$1:$Z$1"), 0))), "") -> 361 | E2: =IF(C2<>"", SUM(INDEX(INDIRECT("'" & B2 & "'.$A$1:$Z$1000"), 0, MATCH("cost", INDIRECT("'" & B2 & "'.$A$1:$Z$1"), 0))), "") -> 36.1 | F2: =IF(C2<>"", SUM(INDEX(INDIRECT("'" & B2 & "'.$A$1:$Z$1000"), 0, MATCH("total_assembly_time_min", INDIRECT("'" & B2 & "'.$A$1:$Z$1"), 0)))/60, "") -> 12.033333 | G2: =IF(C2<>"", values!$B$2, "") -> 14.2 | H2: =IF(C2<>"", F2*G2, "") -> 170.87333 | I2: =IF(C2<>"", H2+E2, "") -> 206.97333 | J2: 0.22 | K2: =IF(C2<>"", L2-I2, "") -> 58.377094 | L2: =IF(C2<>"", I2/(1-J2), "") -> 265.35043 | M2: =IF(C2<>"", values!$A$2, "") -> 0.19 | N2: =IF(C2<>"", O2-L2, "") -> 62.242693 | O2: =IF(C2<>"", L2/(1-M2), "") -> 327.59312
A3: c24212cb-f626-46d0-ac90-8dff482aae99 | B3: bom_00002 | D3: =IF(C3<>"", SUM(INDEX(INDIRECT("'" & B3 & "'.$A$1:$Z$1000"), 0, MATCH("count", INDIRECT("'" & B3 & "'.$A$1:$Z$1"), 0))), "") | E3: =IF(C3<>"", SUM(INDEX(INDIRECT("'" & B3 & "'.$A$1:$Z$1000"), 0, MATCH("cost", INDIRECT("'" & B3 & "'.$A$1:$Z$1"), 0))), "") | F3: =IF(C3<>"", SUM(INDEX(INDIRECT("'" & B3 & "'.$A$1:$Z$1000"), 0, MATCH("total_assembly_time_min", INDIRECT("'" & B3 & "'.$A$1:$Z$1"), 0)))/60, "") | G3: =IF(C3<>"", values!$B$2, "") | H3: =IF(C3<>"", F3*G3, "") | I3: =IF(C3<>"", H3+E3, "") | K3: =IF(C3<>"", L3-I3, "") | L3: =IF(C3<>"", I3/(1-J3), "") | M3: =IF(C3<>"", values!$A$2, "") | N3: =IF(C3<>"", O3-L3, "") | O3: =IF(C3<>"", L3/(1-M3), "")
A4: 0934504c-b9aa-4453-91db-23d6e67012c1 | B4: bom_00003 | D4: =IF(C4<>"", SUM(INDEX(INDIRECT("'" & B4 & "'.$A$1:$Z$1000"), 0, MATCH("count", INDIRECT("'" & B4 & "'.$A$1:$Z$1"), 0))), "") | E4: =IF(C4<>"", SUM(INDEX(INDIRECT("'" & B4 & "'.$A$1:$Z$1000"), 0, MATCH("cost", INDIRECT("'" & B4 & "'.$A$1:$Z$1"), 0))), "") | F4: =IF(C4<>"", SUM(INDEX(INDIRECT("'" & B4 & "'.$A$1:$Z$1000"), 0, MATCH("total_assembly_time_min", INDIRECT("'" & B4 & "'.$A$1:$Z$1"), 0)))/60, "") | G4: =IF(C4<>"", values!$B$2, "") | H4: =IF(C4<>"", F4*G4, "") | I4: =IF(C4<>"", H4+E4, "") | K4: =IF(C4<>"", L4-I4, "") | L4: =IF(C4<>"", I4/(1-J4), "") | M4: =IF(C4<>"", values!$A$2, "") | N4: =IF(C4<>"", O4-L4, "") | O4: =IF(C4<>"", L4/(1-M4), "")
A5: 0410c800-3ad3-4d11-a196-113cfcee60de | B5: bom_00004 | D5: =IF(C5<>"", SUM(INDEX(INDIRECT("'" & B5 & "'.$A$1:$Z$1000"), 0, MATCH("count", INDIRECT("'" & B5 & "'.$A$1:$Z$1"), 0))), "") | E5: =IF(C5<>"", SUM(INDEX(INDIRECT("'" & B5 & "'.$A$1:$Z$1000"), 0, MATCH("cost", INDIRECT("'" & B5 & "'.$A$1:$Z$1"), 0))), "") | F5: =IF(C5<>"", SUM(INDEX(INDIRECT("'" & B5 & "'.$A$1:$Z$1000"), 0, MATCH("total_assembly_time_min", INDIRECT("'" & B5 & "'.$A$1:$Z$1"), 0)))/60, "") | G5: =IF(C5<>"", values!$B$2, "") | H5: =IF(C5<>"", F5*G5, "") | I5: =IF(C5<>"", H5+E5, "") | K5: =IF(C5<>"", L5-I5, "") | L5: =IF(C5<>"", I5/(1-J5), "") | M5: =IF(C5<>"", values!$A$2, "") | N5: =IF(C5<>"", O5-L5, "") | O5: =IF(C5<>"", L5/(1-M5), "")
A6: c7ad9d33-fdc4-40d6-8889-2ee80be2e70a | B6: bom_00005 | D6: =IF(C6<>"", SUM(INDEX(INDIRECT("'" & B6 & "'.$A$1:$Z$1000"), 0, MATCH("count", INDIRECT("'" & B6 & "'.$A$1:$Z$1"), 0))), "") | E6: =IF(C6<>"", SUM(INDEX(INDIRECT("'" & B6 & "'.$A$1:$Z$1000"), 0, MATCH("cost", INDIRECT("'" & B6 & "'.$A$1:$Z$1"), 0))), "") | F6: =IF(C6<>"", SUM(INDEX(INDIRECT("'" & B6 & "'.$A$1:$Z$1000"), 0, MATCH("total_assembly_time_min", INDIRECT("'" & B6 & "'.$A$1:$Z$1"), 0)))/60, "") | G6: =IF(C6<>"", values!$B$2, "") | H6: =IF(C6<>"", F6*G6, "") | I6: =IF(C6<>"", H6+E6, "") | K6: =IF(C6<>"", L6-I6, "") | L6: =IF(C6<>"", I6/(1-J6), "") | M6: =IF(C6<>"", values!$A$2, "") | N6: =IF(C6<>"", O6-L6, "") | O6: =IF(C6<>"", L6/(1-M6), "")
A7: ad4c5d46-f534-426e-9c1d-d8eba03801b0 | B7: bom_00006 | D7: =IF(C7<>"", SUM(INDEX(INDIRECT("'" & B7 & "'.$A$1:$Z$1000"), 0, MATCH("count", INDIRECT("'" & B7 & "'.$A$1:$Z$1"), 0))), "") | E7: =IF(C7<>"", SUM(INDEX(INDIRECT("'" & B7 & "'.$A$1:$Z$1000"), 0, MATCH("cost", INDIRECT("'" & B7 & "'.$A$1:$Z$1"), 0))), "") | F7: =IF(C7<>"", SUM(INDEX(INDIRECT("'" & B7 & "'.$A$1:$Z$1000"), 0, MATCH("total_assembly_time_min", INDIRECT("'" & B7 & "'.$A$1:$Z$1"), 0)))/60, "") | G7: =IF(C7<>"", values!$B$2, "") | H7: =IF(C7<>"", F7*G7, "") | I7: =IF(C7<>"", H7+E7, "") | K7: =IF(C7<>"", L7-I7, "") | L7: =IF(C7<>"", I7/(1-J7), "") | M7: =IF(C7<>"", values!$A$2, "") | N7: =IF(C7<>"", O7-L7, "") | O7: =IF(C7<>"", L7/(1-M7), "")
A8: f3d739cf-66c1-472b-ad98-4dc71b76b0a9 | B8: bom_00007 | D8: =IF(C8<>"", SUM(INDEX(INDIRECT("'" & B8 & "'.$A$1:$Z$1000"), 0, MATCH("count", INDIRECT("'" & B8 & "'.$A$1:$Z$1"), 0))), "") | E8: =IF(C8<>"", SUM(INDEX(INDIRECT("'" & B8 & "'.$A$1:$Z$1000"), 0, MATCH("cost", INDIRECT("'" & B8 & "'.$A$1:$Z$1"), 0))), "") | F8: =IF(C8<>"", SUM(INDEX(INDIRECT("'" & B8 & "'.$A$1:$Z$1000"), 0, MATCH("total_assembly_time_min", INDIRECT("'" & B8 & "'.$A$1:$Z$1"), 0)))/60, "") | G8: =IF(C8<>"", values!$B$2, "") | H8: =IF(C8<>"", F8*G8, "") | I8: =IF(C8<>"", H8+E8, "") | K8: =IF(C8<>"", L8-I8, "") | L8: =IF(C8<>"", I8/(1-J8), "") | M8: =IF(C8<>"", values!$A$2, "") | N8: =IF(C8<>"", O8-L8, "") | O8: =IF(C8<>"", L8/(1-M8), "")
A9: 6ab98022-da09-42af-8d10-e6698156b377 | B9: bom_00008 | D9: =IF(C9<>"", SUM(INDEX(INDIRECT("'" & B9 & "'.$A$1:$Z$1000"), 0, MATCH("count", INDIRECT("'" & B9 & "'.$A$1:$Z$1"), 0))), "") | E9: =IF(C9<>"", SUM(INDEX(INDIRECT("'" & B9 & "'.$A$1:$Z$1000"), 0, MATCH("cost", INDIRECT("'" & B9 & "'.$A$1:$Z$1"), 0))), "") | F9: =IF(C9<>"", SUM(INDEX(INDIRECT("'" & B9 & "'.$A$1:$Z$1000"), 0, MATCH("total_assembly_time_min", INDIRECT("'" & B9 & "'.$A$1:$Z$1"), 0)))/60, "") | G9: =IF(C9<>"", values!$B$2, "") | H9: =IF(C9<>"", F9*G9, "") | I9: =IF(C9<>"", H9+E9, "") | K9: =IF(C9<>"", L9-I9, "") | L9: =IF(C9<>"", I9/(1-J9), "") | M9: =IF(C9<>"", values!$A$2, "") | N9: =IF(C9<>"", O9-L9, "") | O9: =IF(C9<>"", L9/(1-M9), "")
A10: 4f042b8b-b710-4a4e-9d7b-8e0eadc4ff1a | B10: bom_00009 | D10: =IF(C10<>"", SUM(INDEX(INDIRECT("'" & B10 & "'.$A$1:$Z$1000"), 0, MATCH("count", INDIRECT("'" & B10 & "'.$A$1:$Z$1"), 0))), "") | E10: =IF(C10<>"", SUM(INDEX(INDIRECT("'" & B10 & "'.$A$1:$Z$1000"), 0, MATCH("cost", INDIRECT("'" & B10 & "'.$A$1:$Z$1"), 0))), "") | F10: =IF(C10<>"", SUM(INDEX(INDIRECT("'" & B10 & "'.$A$1:$Z$1000"), 0, MATCH("total_assembly_time_min", INDIRECT("'" & B10 & "'.$A$1:$Z$1"), 0)))/60, "") | G10: =IF(C10<>"", values!$B$2, "") | H10: =IF(C10<>"", F10*G10, "") | I10: =IF(C10<>"", H10+E10, "") | K10: =IF(C10<>"", L10-I10, "") | L10: =IF(C10<>"", I10/(1-J10), "") | M10: =IF(C10<>"", values!$A$2, "") | N10: =IF(C10<>"", O10-L10, "") | O10: =IF(C10<>"", L10/(1-M10), "")
A11: c0dab030-d18b-405a-a22f-c2621d058878 | B11: bom_00010 | D11: =IF(C11<>"", SUM(INDEX(INDIRECT("'" & B11 & "'.$A$1:$Z$1000"), 0, MATCH("count", INDIRECT("'" & B11 & "'.$A$1:$Z$1"), 0))), "") | E11: =IF(C11<>"", SUM(INDEX(INDIRECT("'" & B11 & "'.$A$1:$Z$1000"), 0, MATCH("cost", INDIRECT("'" & B11 & "'.$A$1:$Z$1"), 0))), "") | F11: =IF(C11<>"", SUM(INDEX(INDIRECT("'" & B11 & "'.$A$1:$Z$1000"), 0, MATCH("total_assembly_time_min", INDIRECT("'" & B11 & "'.$A$1:$Z$1"), 0)))/60, "") | G11: =IF(C11<>"", values!$B$2, "") | H11: =IF(C11<>"", F11*G11, "") | I11: =IF(C11<>"", H11+E11, "") | K11: =IF(C11<>"", L11-I11, "") | L11: =IF(C11<>"", I11/(1-J11), "") | M11: =IF(C11<>"", values!$A$2, "") | N11: =IF(C11<>"", O11-L11, "") | O11: =IF(C11<>"", L11/(1-M11), "")
A12: 5ba67885-ee33-459d-914b-28bf02910f73 | B12: bom_00011 | D12: =IF(C12<>"", SUM(INDEX(INDIRECT("'" & B12 & "'.$A$1:$Z$1000"), 0, MATCH("count", INDIRECT("'" & B12 & "'.$A$1:$Z$1"), 0))), "") | E12: =IF(C12<>"", SUM(INDEX(INDIRECT("'" & B12 & "'.$A$1:$Z$1000"), 0, MATCH("cost", INDIRECT("'" & B12 & "'.$A$1:$Z$1"), 0))), "") | F12: =IF(C12<>"", SUM(INDEX(INDIRECT("'" & B12 & "'.$A$1:$Z$1000"), 0, MATCH("total_assembly_time_min", INDIRECT("'" & B12 & "'.$A$1:$Z$1"), 0)))/60, "") | G12: =IF(C12<>"", values!$B$2, "") | H12: =IF(C12<>"", F12*G12, "") | I12: =IF(C12<>"", H12+E12, "") | K12: =IF(C12<>"", L12-I12, "") | L12: =IF(C12<>"", I12/(1-J12), "") | M12: =IF(C12<>"", values!$A$2, "") | N12: =IF(C12<>"", O12-L12, "") | O12: =IF(C12<>"", L12/(1-M12), "")
A13: 01e33197-68fd-46d1-8873-9a68c34e12fa | B13: bom_00012 | D13: =IF(C13<>"", SUM(INDEX(INDIRECT("'" & B13 & "'.$A$1:$Z$1000"), 0, MATCH("count", INDIRECT("'" & B13 & "'.$A$1:$Z$1"), 0))), "") | E13: =IF(C13<>"", SUM(INDEX(INDIRECT("'" & B13 & "'.$A$1:$Z$1000"), 0, MATCH("cost", INDIRECT("'" & B13 & "'.$A$1:$Z$1"), 0))), "") | F13: =IF(C13<>"", SUM(INDEX(INDIRECT("'" & B13 & "'.$A$1:$Z$1000"), 0, MATCH("total_assembly_time_min", INDIRECT("'" & B13 & "'.$A$1:$Z$1"), 0)))/60, "") | G13: =IF(C13<>"", values!$B$2, "") | H13: =IF(C13<>"", F13*G13, "") | I13: =IF(C13<>"", H13+E13, "") | K13: =IF(C13<>"", L13-I13, "") | L13: =IF(C13<>"", I13/(1-J13), "") | M13: =IF(C13<>"", values!$A$2, "") | N13: =IF(C13<>"", O13-L13, "") | O13: =IF(C13<>"", L13/(1-M13), "")
A14: a4294605-8b79-4bf7-ba94-720ff256d2b4 | B14: bom_00013 | D14: =IF(C14<>"", SUM(INDEX(INDIRECT("'" & B14 & "'.$A$1:$Z$1000"), 0, MATCH("count", INDIRECT("'" & B14 & "'.$A$1:$Z$1"), 0))), "") | E14: =IF(C14<>"", SUM(INDEX(INDIRECT("'" & B14 & "'.$A$1:$Z$1000"), 0, MATCH("cost", INDIRECT("'" & B14 & "'.$A$1:$Z$1"), 0))), "") | F14: =IF(C14<>"", SUM(INDEX(INDIRECT("'" & B14 & "'.$A$1:$Z$1000"), 0, MATCH("total_assembly_time_min", INDIRECT("'" & B14 & "'.$A$1:$Z$1"), 0)))/60, "") | G14: =IF(C14<>"", values!$B$2, "") | H14: =IF(C14<>"", F14*G14, "") | I14: =IF(C14<>"", H14+E14, "") | K14: =IF(C14<>"", L14-I14, "") | L14: =IF(C14<>"", I14/(1-J14), "") | M14: =IF(C14<>"", values!$A$2, "") | N14: =IF(C14<>"", O14-L14, "") | O14: =IF(C14<>"", L14/(1-M14), "")
... A501: 7126d1d5-8f24-462d-9a7c-b11283ca5996 | B501: bom_00500 | D501: =IF(C501<>"", SUM(INDEX(INDIRECT("'" & B501 & "'.$A$1:$Z$1000"), 0, MATCH("count", INDIRECT("'" & B501 & "'.$A$1:$Z$1"), 0))), "") | E501: =IF(C501<>"", SUM(INDEX(INDIRECT("'" & B501 & "'.$A$1:$Z$1000"), 0, MATCH("cost", INDIRECT("'" & B501 & "'.$A$1:$Z$1"), 0))), "") | F501: =IF(C501<>"", SUM(INDEX(INDIRECT("'" & B501 & "'.$A$1:$Z$1000"), 0, MATCH("total_assembly_time_min", INDIRECT("'" & B501 & "'.$A$1:$Z$1"), 0)))/60, "") | G501: =IF(C501<>"", values!$B$2, "") | H501: =IF(C501<>"", F501*G501, "") | I501: =IF(C501<>"", H501+E501, "") | K501: =IF(C501<>"", L501-I501, "") | L501: =IF(C501<>"", I501/(1-J501), "") | M501: =IF(C501<>"", values!$A$2, "") | N501: =IF(C501<>"", O501-L501, "") | O501: =IF(C501<>"", L501/(1-M501), "")

Sheet bom_00001
A1: component_number | B1: component_usage_context | C1: sub_assembly | D1: count | E1: component_name | F1: cost_per_unit | G1: cost | H1: unit_assembly_time_min | I1: total_assembly_time_min
A2: 000001 | B2: aluminium profile 40x40 1400 mm (mk) | C2: aluminium frame | D2: 4 | E2: =IF(A2<>"", INDEX(components!$D$1:$D$1000, MATCH(A2, components!$C$1:$C$1000, 0)), "") -> Bolt ISO 4762 M3x5 | F2: =IF(A2<>"", INDEX(components!$N$1:$N$1000, MATCH(A2, components!$C$1:$C$1000, 0)), "") -> 0.1 | G2: =IF(A2<>"", F2*D2, "") -> 0.4 | H2: =IF(A2<>"", values!$C$2, "") -> 2 | I2: =IF(A2<>"", H2*D2, "") -> 8
A3: 000001 | B3: aluminium profile 40x40 600 mm (mk) | C3: aluminium frame | D3: 4 | E3: =IF(A3<>"", INDEX(components!$D$1:$D$1000, MATCH(A3, components!$C$1:$C$1000, 0)), "") -> Bolt ISO 4762 M3x5 | F3: =IF(A3<>"", INDEX(components!$N$1:$N$1000, MATCH(A3, components!$C$1:$C$1000, 0)), "") -> 0.1 | G3: =IF(A3<>"", F3*D3, "") -> 0.4 | H3: =IF(A3<>"", values!$C$2, "") -> 2 | I3: =IF(A3<>"", H3*D3, "") -> 8
A4: 000001 | B4: aluminium profile 40x40 700 mm (mk) | C4: aluminium frame | D4: 4 | E4: =IF(A4<>"", INDEX(components!$D$1:$D$1000, MATCH(A4, components!$C$1:$C$1000, 0)), "") -> Bolt ISO 4762 M3x5 | F4: =IF(A4<>"", INDEX(components!$N$1:$N$1000, MATCH(A4, components!$C$1:$C$1000, 0)), "") -> 0.1 | G4: =IF(A4<>"", F4*D4, "") -> 0.4 | H4: =IF(A4<>"", values!$C$2, "") -> 2 | I4: =IF(A4<>"", H4*D4, "") -> 8
A5: 000001 | B5: foot for aluminium frame | C5: aluminium frame | D5: 4 | E5: =IF(A5<>"", INDEX(components!$D$1:$D$1000, MATCH(A5, components!$C$1:$C$1000, 0)), "") -> Bolt ISO 4762 M3x5 | F5: =IF(A5<>"", INDEX(components!$N$1:$N$1000, MATCH(A5, components!$C$1:$C$1000, 0)), "") -> 0.1 | G5: =IF(A5<>"", F5*D5, "") -> 0.4 | H5: =IF(A5<>"", values!$C$2, "") -> 2 | I5: =IF(A5<>"", H5*D5, "") -> 8
A6: 000001 | B6: edge bracket for 40-series aluminium profile | C6: aluminium frame | D6: 16 | E6: =IF(A6<>"", INDEX(components!$D$1:$D$1000, MATCH(A6, components!$C$1:$C$1000, 0)), "") -> Bolt ISO 4762 M3x5 | F6: =IF(A6<>"", INDEX(components!$N$1:$N$1000, MATCH(A6, components!$C$1:$C$1000, 0)), "") -> 0.1 | G6: =IF(A6<>"", F6*D6, "") -> 1.6 | H6: =IF(A6<>"", values!$C$2, "") -> 2 | I6: =IF(A6<>"", H6*D6, "") -> 32
A7: 000001 | B7: screw | C7: aluminium frame | D7: 32 | E7: =IF(A7<>"", INDEX(components!$D$1:$D$1000, MATCH(A7, components!$C$1:$C$1000, 0)), "") -> Bolt ISO 4762 M3x5 | F7: =IF(A7<>"", INDEX(components!$N$1:$N$1000, MATCH(A7, components!$C$1:$C$1000, 0)), "") -> 0.1 | G7: =IF(A7<>"", F7*D7, "") -> 3.2 | H7: =IF(A7<>"", values!$C$2, "") -> 2 | I7: =IF(A7<>"", H7*D7, "") -> 64
A8: 000001 | B8: washer | C8: aluminium frame | D8: 32 | E8: =IF(A8<>"", INDEX(components!$D$1:$D$1000, MATCH(A8, components!$C$1:$C$1000, 0)), "") -> Bolt ISO 4762 M3x5 | F8: =IF(A8<>"", INDEX(components!$N$1:$N$1000, MATCH(A8, components!$C$1:$C$1000, 0)), "") -> 0.1 | G8: =IF(A8<>"", F8*D8, "") -> 3.2 | H8: =IF(A8<>"", values!$C$2, "") -> 2 | I8: =IF(A8<>"", H8*D8, "") -> 64
A9: 000001 | B9: nut | C9: aluminium frame | D9: 32 | E9: =IF(A9<>"", INDEX(components!$D$1:$D$1000, MATCH(A9, components!$C$1:$C$1000, 0)), "") -> Bolt ISO 4762 M3x5 | F9: =IF(A9<>"", INDEX(components!$N$1:$N$1000, MATCH(A9, components!$C$1:$C$1000, 0)), "") -> 0.1 | G9: =IF(A9<>"", F9*D9, "") -> 3.2 | H9: =IF(A9<>"", values!$C$2, "") -> 2 | I9: =IF(A9<>"", H9*D9, "") -> 64
A10: 000001 | B10: mounting base plate | C10: mounting base | D10: 1 | E10: =IF(A10<>"", INDEX(components!$D$1:$D$1000, MATCH(A10, components!$C$1:$C$1000, 0)), "") -> Bolt ISO 4762 M3x5 | F10: =IF(A10<>"", INDEX(components!$N$1:$N$1000, MATCH(A10, components!$C$1:$C$1000, 0)), "") -> 0.1 | G10: =IF(A10<>"", F10*D10, "") -> 0.1 | H10: =IF(A10<>"", values!$C$2, "") -> 2 | I10: =IF(A10<>"", H10*D10, "") -> 2
A11: 000001 | B11: screw | C11: mounting base | D11: 8 | E11: =IF(A11<>"", INDEX(components!$D$1:$D$1000, MATCH(A11, components!$C$1:$C$1000, 0)), "") -> Bolt ISO 4762 M3x5 | F11: =IF(A11<>"", INDEX(components!$N$1:$N$1000, MATCH(A11, components!$C$1:$C$1000, 0)), "") -> 0.1 | G11: =IF(A11<>"", F11*D11, "") -> 0.8 | H11: =IF(A11<>"", values!$C$2, "") -> 2 | I11: =IF(A11<>"", H11*D11, "") -> 16
A12: 000001 | B12: linear guide rail | C12: y-axis | D12: 2 | E12: =IF(A12<>"", INDEX(components!$D$1:$D$1000, MATCH(A12, components!$C$1:$C$1000, 0)), "") -> Bolt ISO 4762 M3x5 | F12: =IF(A12<>"", INDEX(components!$N$1:$N$1000, MATCH(A12, components!$C$1:$C$1000, 0)), "") -> 0.1 | G12: =IF(A12<>"", F12*D12, "") -> 0.2 | H12: =IF(A12<>"", values!$C$2, "") -> 2 | I12: =IF(A12<>"", H12*D12, "") -> 4
A13: 000001 | B13: screw | C13: y-axis | D13: 16 | E13: =IF(A13<>"", INDEX(components!$D$1:$D$1000, MATCH(A13, components!$C$1:$C$1000, 0)), "") -> Bolt ISO 4762 M3x5 | F13: =IF(A13<>"", INDEX(components!$N$1:$N$1000, MATCH(A13, components!$C$1:$C$1000, 0)), "") -> 0.1 | G13: =IF(A13<>"", F13*D13, "") -> 1.6 | H13: =IF(A13<>"", values!$C$2, "") -> 2 | I13: =IF(A13<>"", H13*D13, "") -> 32
... A51: 000001 | B51: gripper | C51: gripper | D51: 1 | E51: =IF(A51<>"", INDEX(components!$D$1:$D$1000, MATCH(A51, components!$C$1:$C$1000, 0)), "") -> Bolt ISO 4762 M3x5 | F51: =IF(A51<>"", INDEX(components!$N$1:$N$1000, MATCH(A51, components!$C$1:$C$1000, 0)), "") -> 0.1 | G51: =IF(A51<>"", F51*D51, "") -> 0.1 | H51: =IF(A51<>"", values!$C$2, "") -> 2 | I51: =IF(A51<>"", H51*D51, "") -> 2
